pyodide_lock/__init__.py
pyodide_lock/cli.py
pyodide_lock/py.typed
pyodide_lock/spec.py
pyodide_lock/utils.py
pyodide_lock-0.1.0a9.dist-info/METADATA
pyodide_lock-0.1.0a9.dist-info/WHEEL
pyodide_lock-0.1.0a9.dist-info/entry_points.txt
pyodide_lock-0.1.0a9.dist-info/licenses/LICENSE
pyodide_lock-0.1.0a9.dist-info/RECORD
